libtruckeefs/__init__.py
libtruckeefs/libtruckeefs.py
libtruckeefs-0.0.7.dist-info/METADATA
libtruckeefs-0.0.7.dist-info/WHEEL
libtruckeefs-0.0.7.dist-info/top_level.txt
libtruckeefs-0.0.7.dist-info/RECORD
