Metadata-Version: 2.4
Name: libtruckeefs
Version: 0.0.7
Summary: None
Home-page: https://git.infrastructure.tech/eons/exe/truckeefs
Author: Eons
Author-email: support@eons.llc
Project-URL: Bug Tracker, https://git.infrastructure.tech/eons/exe/truckeefs/issues
Classifier: Programming Language :: Python :: 3
Classifier: License :: OSI Approved :: GNU Affero General Public License v3 or later (AGPLv3+)
Classifier: Operating System :: OS Independent
Classifier: Development Status :: 4 - Beta
Requires-Python: >=3.10
Requires-Dist: redis[async]
Requires-Dist: eons
Requires-Dist: asyncmy
Requires-Dist: sqlalchemy
Requires-Dist: psutil
Requires-Dist: aiohttp
Requires-Dist: eot
Requires-Dist: libtruckeefs
Requires-Dist: redis
Requires-Dist: aiofiles
Requires-Dist: cryptography
Requires-Dist: sqlalchemy[asyncio]
